importjson/__init__.py
importjson/changelog.py
importjson/importjson.py
importjson/internal.py
importjson/version.py
importjson/templates/module_general.tmpl
importjson-0.2.2.dist-info/DESCRIPTION.rst
importjson-0.2.2.dist-info/METADATA
importjson-0.2.2.dist-info/RECORD
importjson-0.2.2.dist-info/WHEEL
importjson-0.2.2.dist-info/metadata.json
importjson-0.2.2.dist-info/top_level.txt
