Metadata-Version: 2.0
Name: importjson
Version: 0.2.2
Summary: Import a json file as a fully functional module with classes, inheritance, attributes, properties and constraints
Home-page: https://github.com/TonyFlury/py-importjson
Author: Anthony Flury
Author-email: anthony.flury@btinternet.com
License: GNU General Public License (GPL)
Keywords: json development data
Platform: UNKNOWN
Classifier: Development Status :: 5 - Production/Stable
Classifier: Intended Audience :: Developers
Classifier: Topic :: Software Development :: Libraries :: Python Modules
Classifier: License :: OSI Approved :: GNU General Public License (GPL)
Classifier: Programming Language :: Python :: 2.7
Classifier: Programming Language :: Python :: 3.6
Classifier: Programming Language :: Python :: 3.7
Provides-Extra: test
Requires-Dist: six (>=1.10)
Requires-Dist: templatelite (>=0.2.1)
Provides-Extra: test
Requires-Dist: TempDirectoryContext (>=0.0.5a0); extra == 'test'
Requires-Dist: click; extra == 'test'
Requires-Dist: six (>=1.10); extra == 'test'
Requires-Dist: templatelite (>=0.2.1); extra == 'test'
